xnatbidsfns/__init__.py
xnatbidsfns-1.0.dist-info/LICENSE
xnatbidsfns-1.0.dist-info/METADATA
xnatbidsfns-1.0.dist-info/WHEEL
xnatbidsfns-1.0.dist-info/top_level.txt
xnatbidsfns-1.0.dist-info/RECORD
