Metadata-Version: 2.1
Name: xnatbidsfns
Version: 1.0
Summary: Utility functions for BIDS data
Home-page: https://github.com/radiologics/docker-images
Author: Radiologics/NRG
Author-email: kate@radiologics.com
License: UNKNOWN
Platform: UNKNOWN
Classifier: Programming Language :: Python :: 3
Classifier: Programming Language :: Python :: 2
Requires-Python: >=2.6
